eclib/__init__.py
eclib/actuator.py
eclib/bfv.py
eclib/bfv_textbook.py
eclib/colors.py
eclib/controller.py
eclib/dyn_elgamal.py
eclib/elgamal.py
eclib/exceptions.py
eclib/figsetup.py
eclib/figure.py
eclib/gsw.py
eclib/gsw_lwe.py
eclib/modutils.py
eclib/numutils.py
eclib/paillier.py
eclib/plant.py
eclib/primeutils.py
eclib/randutils.py
eclib/regev.py
eclib/rns_bfv.py
eclib/sensor.py
eclib/system.py
eclib-2.0.2.dist-info/LICENSE.txt
eclib-2.0.2.dist-info/METADATA
eclib-2.0.2.dist-info/WHEEL
eclib-2.0.2.dist-info/top_level.txt
eclib-2.0.2.dist-info/RECORD
