Metadata-Version: 2.1
Name: eclib
Version: 2.0.2
Summary: Encrypted Control Library
Home-page: https://github.com/KaoruTeranishi/EncryptedControl
Author: Kaoru Teranishi
Author-email: kaoruteranishi1005@gmail.com
Project-URL: Bug Reports, https://github.com/KaoruTeranishi/EncryptedControl/issues
Project-URL: Source, https://github.com/KaoruTeranishi/EncryptedControl
Keywords: encrypted control,control,cryptography,encryption,homomorphic encryption
Classifier: Development Status :: 5 - Production/Stable
Classifier: Intended Audience :: Science/Research
Classifier: Topic :: Scientific/Engineering
Classifier: License :: OSI Approved :: MIT License
Classifier: Programming Language :: Python :: 3.12
Requires-Python: >=3.12
License-File: LICENSE.txt
Requires-Dist: control
Requires-Dist: matplotlib
Requires-Dist: numpy
